{"expireTime":9007200821739222000,"key":"transformer-remark-markdown-html-ast-85ba8a4dc83db8cfb66d5b4024d1f0f6--","val":{"type":"root","children":[{"type":"element","tagName":"p","properties":{},"children":[{"type":"text","value":" My first professional code project made from scratch to the end. ","position":{"start":{"line":2,"column":1,"offset":1},"end":{"line":2,"column":67,"offset":67}}}],"position":{"start":{"line":2,"column":1,"offset":1},"end":{"line":2,"column":67,"offset":67}}}],"position":{"start":{"line":1,"column":1,"offset":0},"end":{"line":2,"column":67,"offset":67}}}}